{"windows-rwlock.c": [""], "windows-mutex.c": [""], "printf-parse.c": [""], "unictype.in.h": [""], "unictype.h": [""], "regex.c": ["", "regmatch_list", "dynarray_header", "dynarray_finalize_result", "re_string_t", "re_dfa_t", "bin_tree_t", "bin_tree_storage_t", "re_dfastate_t", "re_state_table_entry", "re_backref_cache_entry", "re_fail_stack_ent_t", "re_fail_stack_t"], "printf-parse.h": [""], "windows-initguard.h": [""], "gai_strerror.c": [""], "windows-recmutex.h": [""], "windows-mutex.h": [""], "fatal-signal.c": [""], "windows-once.h": [""], "windows-recmutex.c": [""], "spawn.h": [""], "windows-once.c": [""], "printf-args.h": [""], "wait-process.c": [""], "regex_internal.h": ["", "dynarray_header", "dynarray_finalize_result", "re_string_t", "re_dfa_t", "bin_tree_t", "bin_tree_storage_t", "re_dfastate_t", "re_state_table_entry", "re_backref_cache_entry", "re_fail_stack_ent_t", "re_fail_stack_t"], "vasnprintf.c": [""], "fchdir.c": [""], "regex.h": ["", "re_pattern_buffer"], "windows-rwlock.h": [""], "printf-args.c": [""], "width2.h": [""], "cased.c": [""], "ignorable.c": [""], "tolower.c": [""], "tolower.h": [""], "ignorable.h": [""], "cased.h": [""], "pr_soft_dotted.h": [""], "combiningclass.h": [""], "combiningclass.c": [""], "pr_soft_dotted.c": [""], "hash.h": ["", "hash_tuning", "hash_table"], "res.c": ["", "hash_table", "options", "iri", "file_memory", "file_stat_s", "url", "robot_specs", "path_info"], "hash.c": ["", "hash_tuning", "hash_table", "hash_entry", "options", "iri", "file_memory", "file_stat_s", "cell"], "http.c": ["", "hash_table", "transport_implementation", "urlpos", "options", "iri", "file_memory", "file_stat_s", "url", "hsts_store", "address_list", "ntlmdata", "cookie_jar", "http_stat", "request", "response"], "url.c": ["", "hash_table", "options", "iri", "file_memory", "file_stat_s", "url", "address_list", "scheme_data", "growable"], "http.h": ["", "url"], "ftp-opie.c": ["", "options", "iri", "url", "address_list", "fileinfo"], "connect.h": ["", "transport_implementation", "url", "address_list"], "recur.c": ["", "hash_table", "urlpos", "options", "iri", "file_memory", "file_stat_s", "url", "map_context", "robot_specs", "address_list", "fileinfo", "queue_element", "url_queue"], "ftp.c": ["", "hash_table", "transport_implementation", "urlpos", "options", "iri", "file_memory", "file_stat_s", "url", "address_list", "fileinfo"], "host.c": ["", "hash_table", "options", "iri", "file_memory", "file_stat_s", "url", "address_list", "ptimer", "gaiwt_context"], "ftp-ls.c": ["", "hash_table", "urlpos", "options", "iri", "file_memory", "file_stat_s", "url", "address_list", "fileinfo"], "openssl.c": ["", "hash_table", "transport_implementation", "options", "iri", "file_memory", "file_stat_s", "url", "address_list", "ptimer", "openssl_transport_context"], "init.c": ["", "hash_table", "transport_implementation", "urlpos", "options", "iri", "file_memory", "file_stat_s", "url", "map_context", "robot_specs", "hsts_store", "address_list", "ptimer", "decode_item"], "spider.c": ["", "hash_table", "options", "iri", "file_memory", "file_stat_s", "url", "robot_specs"], "hsts.c": ["", "hash_table", "options", "iri", "file_memory", "file_stat_s", "url", "hsts_store", "address_list", "hsts_kh", "hsts_kh_info"], "connect.c": ["", "hash_table", "transport_implementation", "options", "iri", "file_memory", "file_stat_s", "url", "address_list", "cwt_context", "transport_info"], "convert.c": ["", "hash_table", "urlpos", "options", "iri", "file_memory", "file_stat_s", "url", "map_context", "robot_specs", "ptimer"], "warc.c": ["", "hash_table", "options", "iri", "file_memory", "file_stat_s", "url", "address_list", "warc_cdx_record"], "main.c": ["", "hash_table", "urlpos", "options", "iri", "file_memory", "file_stat_s", "url", "hsts_store", "address_list", "ptimer", "cmdline_option"], "gnutls.c": ["", "hash_table", "transport_implementation", "options", "iri", "file_memory", "file_stat_s", "url", "address_list", "ptimer", "st_read_timer", "wgnutls_transport_context"], "host.h": ["", "url", "address_list"], "warc.h": ["", "url", "address_list"], "ftp-basic.c": ["", "hash_table", "transport_implementation", "options", "iri", "file_memory", "file_stat_s", "url", "address_list", "fileinfo"], "retr.c": ["", "hash_table", "transport_implementation", "urlpos", "options", "iri", "file_memory", "file_stat_s", "url", "map_context", "hsts_store", "address_list", "fileinfo", "ptimer"], "ftp.h": ["", "url", "address_list", "fileinfo"], "html-url.c": ["", "hash_table", "urlpos", "options", "iri", "file_memory", "file_stat_s", "url", "map_context", "attr_pair", "taginfo", "known_tag"], "utils.c": ["", "hash_table", "options", "iri", "file_memory", "file_stat_s"], "html-parse.c": ["", "hash_table", "options", "iri", "file_memory", "file_stat_s", "attr_pair", "taginfo", "pool", "tagstack_item"], "cookies.c": ["", "hash_table", "options", "iri", "file_memory", "file_stat_s", "url", "hsts_store", "cookie_jar", "cookie", "weighed_cookie"], "scratch_buffer.h": ["scratch_buffer"], "canonicalize.c": ["scratch_buffer", "F_triple", "hash_tuning", "hash_table", "realpath_bufs"], "canonicalize-lgpl.c": ["scratch_buffer", "realpath_bufs"], "scratch_buffer_grow.c": ["scratch_buffer"], "scratch_buffer_grow_preserve.c": ["scratch_buffer"], "scratch_buffer_set_array_size.c": ["scratch_buffer"], "scratch_buffer.gl.h": ["scratch_buffer"], "hash-triple.h": ["F_triple"], "hash-triple-simple.c": ["F_triple"], "file-set.c": ["F_triple", "hash_tuning", "hash_table"], "mbchar.c": ["mbchar"], "mbiter.c": ["mbchar", "mbiter_multi"], "mbchar.h": ["mbchar"], "mbiter.h": ["mbchar", "mbiter_multi"], "sys_socket.in.h": ["msghdr"], "md2.h": ["md2_ctx"], "md2.c": ["md2_ctx"], "md2-stream.c": ["md2_ctx"], "file-set.h": ["hash_tuning", "hash_table"], "css-url.c": ["hash_table", "urlpos", "options", "iri", "file_memory", "file_stat_s", "url", "map_context", "yy_buffer_state"], "xattr.c": ["hash_table", "options", "iri", "file_memory", "file_stat_s", "url"], "netrc.c": ["hash_table", "options", "iri", "file_memory", "file_stat_s", "_acc_t"], "html-url.h": ["hash_table", "urlpos", "options", "iri", "file_memory", "file_stat_s", "url", "map_context"], "utils.h": ["hash_table", "options", "iri", "file_memory", "file_stat_s"], "log.c": ["hash_table", "options", "iri", "file_memory", "file_stat_s", "log_ln", "logvprintf_state", "ringel"], "http-ntlm.c": ["hash_table", "options", "iri", "file_memory", "file_stat_s", "ntlmdata"], "iri.c": ["hash_table", "options", "iri", "file_memory", "file_stat_s", "url"], "ptimer.c": ["hash_table", "options", "iri", "file_memory", "file_stat_s", "ptimer"], "mswindows.c": ["hash_table", "options", "iri", "file_memory", "file_stat_s", "url", "fake_fork_info", "thread_data"], "convert.h": ["hash_table", "urlpos", "url"], "html-parse.h": ["hash_table", "attr_pair", "taginfo"], "progress.c": ["hash_table", "options", "iri", "file_memory", "file_stat_s", "url", "progress_implementation", "dot_progress", "bar_progress"], "localcharset.c": ["table_entry"], "getopt-pfx-ext.h": ["option"], "getopt.in.h": ["option"], "sha256.c": ["sha256_ctx"], "sha256.h": ["sha256_ctx"], "sha256-stream.c": ["sha256_ctx"], "spawn_faction_init.c": ["__spawn_action"], "spawn.c": ["__spawn_action"], "spawn_int.h": ["__spawn_action"], "spawni.c": ["__spawn_action"], "spawnp.c": ["__spawn_action"], "quote.h": ["quoting_options"], "quotearg.h": ["quoting_options"], "quotearg.c": ["quoting_options", "slotvec"], "sha1.h": ["sha1_ctx"], "sha1.c": ["sha1_ctx"], "sha1-stream.c": ["sha1_ctx"], "fnmatch_loop.c": ["STRUCT"], "fnmatch.c": ["STRUCT", "fnmatch_struct"], "md5.c": ["md5_ctx"], "md5-stream.c": ["md5_ctx"], "md5.h": ["md5_ctx"], "fdopendir.c": ["saved_cwd"], "openat.c": ["saved_cwd"], "fstatat.c": ["saved_cwd"], "save-cwd.c": ["saved_cwd"], "save-cwd.h": ["saved_cwd"], "at-func.c": ["saved_cwd"], "regexec.c": ["regmatch_list"], "md4.h": ["md4_ctx"], "md4-stream.c": ["md4_ctx"], "md4.c": ["md4_ctx"], "uninorm.in.h": ["unicode_normalization_form", "uninorm_filter"], "unicase.h": ["unicode_normalization_form", "uninorm_filter", "casing_prefix_context", "casing_suffix_context"], "uninorm.h": ["unicode_normalization_form", "uninorm_filter"], "unicase.in.h": ["unicode_normalization_form", "uninorm_filter", "casing_prefix_context", "casing_suffix_context"], "u8-normalize.c": ["unicode_normalization_form"], "normalize-internal.h": ["unicode_normalization_form"], "regcomp.c": ["re_pattern_buffer"], "dynarray.h": ["dynarray_header", "dynarray_finalize_result"], "dynarray_resize_clear.c": ["dynarray_header", "dynarray_finalize_result"], "dynarray_at_failure.c": ["dynarray_header", "dynarray_finalize_result"], "dynarray_finalize.c": ["dynarray_header", "dynarray_finalize_result"], "dynarray_emplace_enlarge.c": ["dynarray_header", "dynarray_finalize_result"], "dynarray.gl.h": ["dynarray_header", "dynarray_finalize_result"], "dynarray_resize.c": ["dynarray_header", "dynarray_finalize_result"], "sha512.c": ["sha512_ctx"], "sha512-stream.c": ["sha512_ctx"], "sha512.h": ["sha512_ctx"], "base32.c": ["base32_decode_context"], "base32.h": ["base32_decode_context"], "windows-spawn.h": ["IHANDLE", "inheritable_handles"], "windows-spawn.c": ["IHANDLE", "inheritable_handles"], "group-member.c": ["group_info"], "dirent-private.h": ["gl_directory"], "getopt_int.h": ["_getopt_data"], "getopt1.c": ["_getopt_data"], "getopt.c": ["_getopt_data"], "time.h": ["__time_t_must_be_integral"], "chdir-long.c": ["cd_buf"], "decompose-internal.h": ["ucs4_with_ccc"], "decompose-internal.c": ["ucs4_with_ccc"], "special-casing.h": ["special_casing_rule"], "special-casing-table.h": ["special_casing_rule"], "special-casing.in.h": ["special_casing_rule"], "dynarray-skeleton.c": ["DYNARRAY_STRUCT"], "dynarray-skeleton.gl.h": ["DYNARRAY_STRUCT"], "wget_read_hunk_fuzzer.c": ["my_context", "transport_implementation"], "css-url.h": ["urlpos"], "recur.h": ["urlpos", "url"], "wget.h": ["options", "iri"], "exits.h": ["options", "iri"], "metalink.c": ["options", "iri"], "build_info.c": ["options", "iri"], "exits.c": ["options", "iri"], "css_.c": ["options", "iri", "yy_buffer_state", "yy_trans_info"], "options.h": ["options"], "iri.h": ["iri"], "xattr.h": ["url"], "retr.h": ["url"], "url.h": ["url"], "css.c": ["yy_buffer_state", "yy_trans_info"], "res.h": ["robot_specs"], "http-ntlm.h": ["ntlmdata"], "cookies.h": ["cookie_jar"], "ptimer.h": ["ptimer"]}