[
    {
        "arguments": [
            "cc",
            "-c",
            "-DHAVE_CONFIG_H",
            "-I.",
            "-I..",
            "-g",
            "-O2",
            "-o",
            "argp-fmtstream.o",
            "argp-fmtstream.c"
        ],
        "directory": "/home/c2rust/Desktop/c_prog/tar-1.34/gnu",
        "file": "argp-fmtstream.c"
    },
    {
        "arguments": [
            "cc",
            "-c",
            "-DHAVE_CONFIG_H",
            "-I.",
            "-I..",
            "-I../gnu",
            "-I../",
            "-I../gnu",
            "-I../lib",
            "-I../lib",
            "-g",
            "-O2",
            "-o",
            "extract.o",
            "extract.c"
        ],
        "directory": "/home/c2rust/Desktop/c_prog/tar-1.34/src",
        "file": "extract.c"
    },
    {
        "arguments": [
            "cc",
            "-c",
            "-DHAVE_CONFIG_H",
            "-I.",
            "-I..",
            "-g",
            "-O2",
            "-o",
            "malloc/scratch_buffer_grow_preserve.o",
            "malloc/scratch_buffer_grow_preserve.c"
        ],
        "directory": "/home/c2rust/Desktop/c_prog/tar-1.34/gnu",
        "file": "malloc/scratch_buffer_grow_preserve.c"
    },
    {
        "arguments": [
            "cc",
            "-c",
            "-DHAVE_CONFIG_H",
            "-I.",
            "-I..",
            "-g",
            "-O2",
            "-o",
            "file-has-acl.o",
            "file-has-acl.c"
        ],
        "directory": "/home/c2rust/Desktop/c_prog/tar-1.34/gnu",
        "file": "file-has-acl.c"
    },
    {
        "arguments": [
            "cc",
            "-c",
            "-DHAVE_CONFIG_H",
            "-I.",
            "-I..",
            "-g",
            "-O2",
            "-o",
            "xstrtoumax.o",
            "xstrtoumax.c"
        ],
        "directory": "/home/c2rust/Desktop/c_prog/tar-1.34/gnu",
        "file": "xstrtoumax.c"
    },
    {
        "arguments": [
            "cc",
            "-c",
            "-DHAVE_CONFIG_H",
            "-I.",
            "-I..",
            "-I../gnu",
            "-I../",
            "-I../gnu",
            "-I../lib",
            "-I../lib",
            "-g",
            "-O2",
            "-o",
            "tar.o",
            "tar.c"
        ],
        "directory": "/home/c2rust/Desktop/c_prog/tar-1.34/src",
        "file": "tar.c"
    },
    {
        "arguments": [
            "cc",
            "-c",
            "-DHAVE_CONFIG_H",
            "-I.",
            "-I..",
            "-g",
            "-O2",
            "-o",
            "xasprintf.o",
            "xasprintf.c"
        ],
        "directory": "/home/c2rust/Desktop/c_prog/tar-1.34/gnu",
        "file": "xasprintf.c"
    },
    {
        "arguments": [
            "cc",
            "-c",
            "-DHAVE_CONFIG_H",
            "-I.",
            "-I..",
            "-g",
            "-O2",
            "-o",
            "hard-locale.o",
            "hard-locale.c"
        ],
        "directory": "/home/c2rust/Desktop/c_prog/tar-1.34/gnu",
        "file": "hard-locale.c"
    },
    {
        "arguments": [
            "cc",
            "-c",
            "-DHAVE_CONFIG_H",
            "-I.",
            "-I..",
            "-g",
            "-O2",
            "-o",
            "localcharset.o",
            "localcharset.c"
        ],
        "directory": "/home/c2rust/Desktop/c_prog/tar-1.34/gnu",
        "file": "localcharset.c"
    },
    {
        "arguments": [
            "cc",
            "-c",
            "-DHAVE_CONFIG_H",
            "-I.",
            "-I..",
            "-g",
            "-O2",
            "-o",
            "uinttostr.o",
            "uinttostr.c"
        ],
        "directory": "/home/c2rust/Desktop/c_prog/tar-1.34/gnu",
        "file": "uinttostr.c"
    },
    {
        "arguments": [
            "cc",
            "-c",
            "-DHAVE_CONFIG_H",
            "-I.",
            "-I..",
            "-g",
            "-O2",
            "-o",
            "getopt1.o",
            "getopt1.c"
        ],
        "directory": "/home/c2rust/Desktop/c_prog/tar-1.34/gnu",
        "file": "getopt1.c"
    },
    {
        "arguments": [
            "cc",
            "-c",
            "-DHAVE_CONFIG_H",
            "-I.",
            "-I..",
            "-g",
            "-O2",
            "-o",
            "stdopen.o",
            "stdopen.c"
        ],
        "directory": "/home/c2rust/Desktop/c_prog/tar-1.34/gnu",
        "file": "stdopen.c"
    },
    {
        "arguments": [
            "cc",
            "-c",
            "-DHAVE_CONFIG_H",
            "-I.",
            "-I..",
            "-g",
            "-O2",
            "-o",
            "c-strncasecmp.o",
            "c-strncasecmp.c"
        ],
        "directory": "/home/c2rust/Desktop/c_prog/tar-1.34/gnu",
        "file": "c-strncasecmp.c"
    },
    {
        "arguments": [
            "cc",
            "-c",
            "-DHAVE_CONFIG_H",
            "-I.",
            "-I..",
            "-g",
            "-O2",
            "-o",
            "unistd.o",
            "unistd.c"
        ],
        "directory": "/home/c2rust/Desktop/c_prog/tar-1.34/gnu",
        "file": "unistd.c"
    },
    {
        "arguments": [
            "cc",
            "-c",
            "-DHAVE_CONFIG_H",
            "-I.",
            "-I..",
            "-g",
            "-O2",
            "-o",
            "printf-args.o",
            "printf-args.c"
        ],
        "directory": "/home/c2rust/Desktop/c_prog/tar-1.34/gnu",
        "file": "printf-args.c"
    },
    {
        "arguments": [
            "cc",
            "-c",
            "-DHAVE_CONFIG_H",
            "-I.",
            "-I..",
            "-g",
            "-O2",
            "-o",
            "uniwidth/width.o",
            "uniwidth/width.c"
        ],
        "directory": "/home/c2rust/Desktop/c_prog/tar-1.34/gnu",
        "file": "uniwidth/width.c"
    },
    {
        "arguments": [
            "cc",
            "-c",
            "-DHAVE_CONFIG_H",
            "-I.",
            "-I..",
            "-g",
            "-O2",
            "-o",
            "argp-ba.o",
            "argp-ba.c"
        ],
        "directory": "/home/c2rust/Desktop/c_prog/tar-1.34/gnu",
        "file": "argp-ba.c"
    },
    {
        "arguments": [
            "cc",
            "-c",
            "-DHAVE_CONFIG_H",
            "-I.",
            "-I..",
            "-g",
            "-O2",
            "-o",
            "full-write.o",
            "full-write.c"
        ],
        "directory": "/home/c2rust/Desktop/c_prog/tar-1.34/gnu",
        "file": "full-write.c"
    },
    {
        "arguments": [
            "cc",
            "-c",
            "-DHAVE_CONFIG_H",
            "-I.",
            "-I..",
            "-g",
            "-O2",
            "-o",
            "statat.o",
            "statat.c"
        ],
        "directory": "/home/c2rust/Desktop/c_prog/tar-1.34/gnu",
        "file": "statat.c"
    },
    {
        "arguments": [
            "cc",
            "-c",
            "-DHAVE_CONFIG_H",
            "-I.",
            "-I..",
            "-g",
            "-O2",
            "-o",
            "save-cwd.o",
            "save-cwd.c"
        ],
        "directory": "/home/c2rust/Desktop/c_prog/tar-1.34/gnu",
        "file": "save-cwd.c"
    },
    {
        "arguments": [
            "cc",
            "-c",
            "-DHAVE_CONFIG_H",
            "-I.",
            "-I..",
            "-g",
            "-O2",
            "-o",
            "obstack.o",
            "obstack.c"
        ],
        "directory": "/home/c2rust/Desktop/c_prog/tar-1.34/gnu",
        "file": "obstack.c"
    },
    {
        "arguments": [
            "cc",
            "-c",
            "-DHAVE_CONFIG_H",
            "-I.",
            "-I..",
            "-I../gnu",
            "-I../",
            "-I../gnu",
            "-I../lib",
            "-I../lib",
            "-g",
            "-O2",
            "-o",
            "map.o",
            "map.c"
        ],
        "directory": "/home/c2rust/Desktop/c_prog/tar-1.34/src",
        "file": "map.c"
    },
    {
        "arguments": [
            "cc",
            "-c",
            "-DHAVE_CONFIG_H",
            "-I.",
            "-I..",
            "-g",
            "-O2",
            "-o",
            "argp-parse.o",
            "argp-parse.c"
        ],
        "directory": "/home/c2rust/Desktop/c_prog/tar-1.34/gnu",
        "file": "argp-parse.c"
    },
    {
        "arguments": [
            "cc",
            "-c",
            "-DHAVE_CONFIG_H",
            "-I.",
            "-I..",
            "-g",
            "-O2",
            "-o",
            "mbrtowc.o",
            "mbrtowc.c"
        ],
        "directory": "/home/c2rust/Desktop/c_prog/tar-1.34/gnu",
        "file": "mbrtowc.c"
    },
    {
        "arguments": [
            "cc",
            "-c",
            "-DHAVE_CONFIG_H",
            "-I.",
            "-I..",
            "-g",
            "-O2",
            "-o",
            "strnlen1.o",
            "strnlen1.c"
        ],
        "directory": "/home/c2rust/Desktop/c_prog/tar-1.34/gnu",
        "file": "strnlen1.c"
    },
    {
        "arguments": [
            "cc",
            "-c",
            "-DHAVE_CONFIG_H",
            "-I.",
            "-I..",
            "-g",
            "-O2",
            "-o",
            "fprintftime.o",
            "fprintftime.c"
        ],
        "directory": "/home/c2rust/Desktop/c_prog/tar-1.34/gnu",
        "file": "fprintftime.c"
    },
    {
        "arguments": [
            "cc",
            "-c",
            "-DHAVE_CONFIG_H",
            "-I.",
            "-I..",
            "-g",
            "-O2",
            "-o",
            "umaxtostr.o",
            "umaxtostr.c"
        ],
        "directory": "/home/c2rust/Desktop/c_prog/tar-1.34/gnu",
        "file": "umaxtostr.c"
    },
    {
        "arguments": [
            "cc",
            "-c",
            "-DHAVE_CONFIG_H",
            "-I.",
            "-I..",
            "-g",
            "-O2",
            "-o",
            "tempname.o",
            "tempname.c"
        ],
        "directory": "/home/c2rust/Desktop/c_prog/tar-1.34/gnu",
        "file": "tempname.c"
    },
    {
        "arguments": [
            "cc",
            "-c",
            "-DHAVE_CONFIG_H",
            "-I.",
            "-I..",
            "-g",
            "-O2",
            "-o",
            "getopt.o",
            "getopt.c"
        ],
        "directory": "/home/c2rust/Desktop/c_prog/tar-1.34/gnu",
        "file": "getopt.c"
    },
    {
        "arguments": [
            "cc",
            "-c",
            "-DHAVE_CONFIG_H",
            "-I.",
            "-I..",
            "-g",
            "-O2",
            "-o",
            "opendirat.o",
            "opendirat.c"
        ],
        "directory": "/home/c2rust/Desktop/c_prog/tar-1.34/gnu",
        "file": "opendirat.c"
    },
    {
        "arguments": [
            "cc",
            "-c",
            "-DHAVE_CONFIG_H",
            "-I.",
            "-I..",
            "-g",
            "-O2",
            "-o",
            "closeout.o",
            "closeout.c"
        ],
        "directory": "/home/c2rust/Desktop/c_prog/tar-1.34/gnu",
        "file": "closeout.c"
    },
    {
        "arguments": [
            "cc",
            "-c",
            "-DHAVE_CONFIG_H",
            "-I.",
            "-I..",
            "-g",
            "-O2",
            "-o",
            "argmatch.o",
            "argmatch.c"
        ],
        "directory": "/home/c2rust/Desktop/c_prog/tar-1.34/gnu",
        "file": "argmatch.c"
    },
    {
        "arguments": [
            "cc",
            "-c",
            "-DHAVE_CONFIG_H",
            "-I.",
            "-I..",
            "-g",
            "-O2",
            "-o",
            "dup-safer.o",
            "dup-safer.c"
        ],
        "directory": "/home/c2rust/Desktop/c_prog/tar-1.34/gnu",
        "file": "dup-safer.c"
    },
    {
        "arguments": [
            "cc",
            "-c",
            "-DHAVE_CONFIG_H",
            "-I.",
            "-I..",
            "-g",
            "-O2",
            "-o",
            "creat-safer.o",
            "creat-safer.c"
        ],
        "directory": "/home/c2rust/Desktop/c_prog/tar-1.34/gnu",
        "file": "creat-safer.c"
    },
    {
        "arguments": [
            "cc",
            "-c",
            "-DHAVE_CONFIG_H",
            "-I.",
            "-I..",
            "-g",
            "-O2",
            "-o",
            "utimens.o",
            "utimens.c"
        ],
        "directory": "/home/c2rust/Desktop/c_prog/tar-1.34/gnu",
        "file": "utimens.c"
    },
    {
        "arguments": [
            "cc",
            "-c",
            "-DHAVE_CONFIG_H",
            "-I.",
            "-I..",
            "-I../gnu",
            "-I../",
            "-I../gnu",
            "-g",
            "-O2",
            "-o",
            "paxexit-status.o",
            "paxexit-status.c"
        ],
        "directory": "/home/c2rust/Desktop/c_prog/tar-1.34/lib",
        "file": "paxexit-status.c"
    },
    {
        "arguments": [
            "cc",
            "-c",
            "-DHAVE_CONFIG_H",
            "-I.",
            "-I..",
            "-g",
            "-O2",
            "-o",
            "nstrftime.o",
            "nstrftime.c"
        ],
        "directory": "/home/c2rust/Desktop/c_prog/tar-1.34/gnu",
        "file": "nstrftime.c"
    },
    {
        "arguments": [
            "cc",
            "-c",
            "-DHAVE_CONFIG_H",
            "-I.",
            "-I..",
            "-g",
            "-O2",
            "-o",
            "renameatu.o",
            "renameatu.c"
        ],
        "directory": "/home/c2rust/Desktop/c_prog/tar-1.34/gnu",
        "file": "renameatu.c"
    },
    {
        "arguments": [
            "cc",
            "-c",
            "-DHAVE_CONFIG_H",
            "-I.",
            "-I..",
            "-g",
            "-O2",
            "-o",
            "openat-safer.o",
            "openat-safer.c"
        ],
        "directory": "/home/c2rust/Desktop/c_prog/tar-1.34/gnu",
        "file": "openat-safer.c"
    },
    {
        "arguments": [
            "cc",
            "-c",
            "-DHAVE_CONFIG_H",
            "-I.",
            "-I..",
            "-g",
            "-O2",
            "-o",
            "acl-errno-valid.o",
            "acl-errno-valid.c"
        ],
        "directory": "/home/c2rust/Desktop/c_prog/tar-1.34/gnu",
        "file": "acl-errno-valid.c"
    },
    {
        "arguments": [
            "cc",
            "-c",
            "-DHAVE_CONFIG_H",
            "-I.",
            "-I..",
            "-g",
            "-O2",
            "-o",
            "malloca.o",
            "malloca.c"
        ],
        "directory": "/home/c2rust/Desktop/c_prog/tar-1.34/gnu",
        "file": "malloca.c"
    },
    {
        "arguments": [
            "cc",
            "-c",
            "-DHAVE_CONFIG_H",
            "-I.",
            "-I..",
            "-g",
            "-O2",
            "-o",
            "lchmod.o",
            "lchmod.c"
        ],
        "directory": "/home/c2rust/Desktop/c_prog/tar-1.34/gnu",
        "file": "lchmod.c"
    },
    {
        "arguments": [
            "cc",
            "-c",
            "-DHAVE_CONFIG_H",
            "-I.",
            "-I..",
            "-I../gnu",
            "-I../",
            "-I../gnu",
            "-I../lib",
            "-I../lib",
            "-g",
            "-O2",
            "-o",
            "incremen.o",
            "incremen.c"
        ],
        "directory": "/home/c2rust/Desktop/c_prog/tar-1.34/src",
        "file": "incremen.c"
    },
    {
        "arguments": [
            "cc",
            "-c",
            "-DHAVE_CONFIG_H",
            "-I.",
            "-I..",
            "-g",
            "-O2",
            "-o",
            "cloexec.o",
            "cloexec.c"
        ],
        "directory": "/home/c2rust/Desktop/c_prog/tar-1.34/gnu",
        "file": "cloexec.c"
    },
    {
        "arguments": [
            "cc",
            "-c",
            "-DHAVE_CONFIG_H",
            "-I.",
            "-I..",
            "-g",
            "-O2",
            "-o",
            "dirname-lgpl.o",
            "dirname-lgpl.c"
        ],
        "directory": "/home/c2rust/Desktop/c_prog/tar-1.34/gnu",
        "file": "dirname-lgpl.c"
    },
    {
        "arguments": [
            "cc",
            "-c",
            "-DHAVE_CONFIG_H",
            "-I.",
            "-I..",
            "-g",
            "-O2",
            "-o",
            "setlocale_null.o",
            "setlocale_null.c"
        ],
        "directory": "/home/c2rust/Desktop/c_prog/tar-1.34/gnu",
        "file": "setlocale_null.c"
    },
    {
        "arguments": [
            "cc",
            "-c",
            "-DHAVE_CONFIG_H",
            "-I.",
            "-I..",
            "-g",
            "-O2",
            "-o",
            "argp-help.o",
            "argp-help.c"
        ],
        "directory": "/home/c2rust/Desktop/c_prog/tar-1.34/gnu",
        "file": "argp-help.c"
    },
    {
        "arguments": [
            "cc",
            "-c",
            "-DHAVE_CONFIG_H",
            "-I.",
            "-I..",
            "-g",
            "-O2",
            "-o",
            "xstrtoul.o",
            "xstrtoul.c"
        ],
        "directory": "/home/c2rust/Desktop/c_prog/tar-1.34/gnu",
        "file": "xstrtoul.c"
    },
    {
        "arguments": [
            "cc",
            "-c",
            "-DHAVE_CONFIG_H",
            "-I.",
            "-I..",
            "-g",
            "-O2",
            "-o",
            "se-selinux.o",
            "se-selinux.c"
        ],
        "directory": "/home/c2rust/Desktop/c_prog/tar-1.34/gnu",
        "file": "se-selinux.c"
    },
    {
        "arguments": [
            "cc",
            "-c",
            "-DHAVE_CONFIG_H",
            "-I.",
            "-I..",
            "-g",
            "-O2",
            "-o",
            "fd-safer.o",
            "fd-safer.c"
        ],
        "directory": "/home/c2rust/Desktop/c_prog/tar-1.34/gnu",
        "file": "fd-safer.c"
    },
    {
        "arguments": [
            "cc",
            "-c",
            "-DHAVE_CONFIG_H",
            "-I.",
            "-I..",
            "-g",
            "-O2",
            "-o",
            "quotearg.o",
            "quotearg.c"
        ],
        "directory": "/home/c2rust/Desktop/c_prog/tar-1.34/gnu",
        "file": "quotearg.c"
    },
    {
        "arguments": [
            "cc",
            "-c",
            "-DHAVE_CONFIG_H",
            "-I.",
            "-I..",
            "-I../gnu",
            "-I../",
            "-I../gnu",
            "-I../lib",
            "-I../lib",
            "-g",
            "-O2",
            "-o",
            "checkpoint.o",
            "checkpoint.c"
        ],
        "directory": "/home/c2rust/Desktop/c_prog/tar-1.34/src",
        "file": "checkpoint.c"
    },
    {
        "arguments": [
            "cc",
            "-c",
            "-DHAVE_CONFIG_H",
            "-I.",
            "-I..",
            "-I../gnu",
            "-I../",
            "-I../gnu",
            "-I../lib",
            "-I../lib",
            "-g",
            "-O2",
            "-o",
            "update.o",
            "update.c"
        ],
        "directory": "/home/c2rust/Desktop/c_prog/tar-1.34/src",
        "file": "update.c"
    },
    {
        "arguments": [
            "cc",
            "-c",
            "-DHAVE_CONFIG_H",
            "-I.",
            "-I..",
            "-g",
            "-O2",
            "-o",
            "mbscasecmp.o",
            "mbscasecmp.c"
        ],
        "directory": "/home/c2rust/Desktop/c_prog/tar-1.34/gnu",
        "file": "mbscasecmp.c"
    },
    {
        "arguments": [
            "cc",
            "-c",
            "-DHAVE_CONFIG_H",
            "-I.",
            "-I..",
            "-g",
            "-O2",
            "-o",
            "backup-find.o",
            "backup-find.c"
        ],
        "directory": "/home/c2rust/Desktop/c_prog/tar-1.34/gnu",
        "file": "backup-find.c"
    },
    {
        "arguments": [
            "cc",
            "-c",
            "-DHAVE_CONFIG_H",
            "-I.",
            "-I..",
            "-g",
            "-O2",
            "-o",
            "xvasprintf.o",
            "xvasprintf.c"
        ],
        "directory": "/home/c2rust/Desktop/c_prog/tar-1.34/gnu",
        "file": "xvasprintf.c"
    },
    {
        "arguments": [
            "cc",
            "-c",
            "-DHAVE_CONFIG_H",
            "-I.",
            "-I..",
            "-I../gnu",
            "-I../",
            "-I../gnu",
            "-g",
            "-O2",
            "-o",
            "xattr-at.o",
            "xattr-at.c"
        ],
        "directory": "/home/c2rust/Desktop/c_prog/tar-1.34/lib",
        "file": "xattr-at.c"
    },
    {
        "arguments": [
            "cc",
            "-c",
            "-DHAVE_CONFIG_H",
            "-I.",
            "-I..",
            "-I../gnu",
            "-I../",
            "-I../gnu",
            "-g",
            "-O2",
            "-o",
            "paxnames.o",
            "paxnames.c"
        ],
        "directory": "/home/c2rust/Desktop/c_prog/tar-1.34/lib",
        "file": "paxnames.c"
    },
    {
        "arguments": [
            "cc",
            "-c",
            "-DHAVE_CONFIG_H",
            "-I.",
            "-I..",
            "-g",
            "-O2",
            "-o",
            "printf-parse.o",
            "printf-parse.c"
        ],
        "directory": "/home/c2rust/Desktop/c_prog/tar-1.34/gnu",
        "file": "printf-parse.c"
    },
    {
        "arguments": [
            "cc",
            "-c",
            "-DHAVE_CONFIG_H",
            "-I.",
            "-I..",
            "-I../gnu",
            "-I../",
            "-I../gnu",
            "-I../lib",
            "-g",
            "-O2",
            "-o",
            "rmt.o",
            "rmt.c"
        ],
        "directory": "/home/c2rust/Desktop/c_prog/tar-1.34/rmt",
        "file": "rmt.c"
    },
    {
        "arguments": [
            "cc",
            "-c",
            "-DHAVE_CONFIG_H",
            "-I.",
            "-I..",
            "-I../gnu",
            "-I../",
            "-I../gnu",
            "-g",
            "-O2",
            "-o",
            "rtapelib.o",
            "rtapelib.c"
        ],
        "directory": "/home/c2rust/Desktop/c_prog/tar-1.34/lib",
        "file": "rtapelib.c"
    },
    {
        "arguments": [
            "cc",
            "-c",
            "-DHAVE_CONFIG_H",
            "-I.",
            "-I..",
            "-g",
            "-O2",
            "-o",
            "areadlink.o",
            "areadlink.c"
        ],
        "directory": "/home/c2rust/Desktop/c_prog/tar-1.34/gnu",
        "file": "areadlink.c"
    },
    {
        "arguments": [
            "cc",
            "-c",
            "-DHAVE_CONFIG_H",
            "-I.",
            "-I..",
            "-g",
            "-O2",
            "-o",
            "selinux-at.o",
            "selinux-at.c"
        ],
        "directory": "/home/c2rust/Desktop/c_prog/tar-1.34/gnu",
        "file": "selinux-at.c"
    },
    {
        "arguments": [
            "cc",
            "-c",
            "-DHAVE_CONFIG_H",
            "-I.",
            "-I..",
            "-I../gnu",
            "-I../",
            "-I../gnu",
            "-I../lib",
            "-I../lib",
            "-g",
            "-O2",
            "-o",
            "transform.o",
            "transform.c"
        ],
        "directory": "/home/c2rust/Desktop/c_prog/tar-1.34/src",
        "file": "transform.c"
    },
    {
        "arguments": [
            "cc",
            "-c",
            "-DHAVE_CONFIG_H",
            "-I.",
            "-I..",
            "-g",
            "-O2",
            "-o",
            "open-safer.o",
            "open-safer.c"
        ],
        "directory": "/home/c2rust/Desktop/c_prog/tar-1.34/gnu",
        "file": "open-safer.c"
    },
    {
        "arguments": [
            "cc",
            "-c",
            "-DHAVE_CONFIG_H",
            "-I.",
            "-I..",
            "-g",
            "-O2",
            "-o",
            "argp-pin.o",
            "argp-pin.c"
        ],
        "directory": "/home/c2rust/Desktop/c_prog/tar-1.34/gnu",
        "file": "argp-pin.c"
    },
    {
        "arguments": [
            "cc",
            "-c",
            "-DHAVE_CONFIG_H",
            "-I.",
            "-I..",
            "-g",
            "-O2",
            "-o",
            "allocator.o",
            "allocator.c"
        ],
        "directory": "/home/c2rust/Desktop/c_prog/tar-1.34/gnu",
        "file": "allocator.c"
    },
    {
        "arguments": [
            "cc",
            "-c",
            "-DHAVE_CONFIG_H",
            "-I.",
            "-I..",
            "-g",
            "-O2",
            "-o",
            "malloc/scratch_buffer_grow.o",
            "malloc/scratch_buffer_grow.c"
        ],
        "directory": "/home/c2rust/Desktop/c_prog/tar-1.34/gnu",
        "file": "malloc/scratch_buffer_grow.c"
    },
    {
        "arguments": [
            "cc",
            "-c",
            "-DHAVE_CONFIG_H",
            "-I.",
            "-I..",
            "-g",
            "-O2",
            "-o",
            "areadlink-with-size.o",
            "areadlink-with-size.c"
        ],
        "directory": "/home/c2rust/Desktop/c_prog/tar-1.34/gnu",
        "file": "areadlink-with-size.c"
    },
    {
        "arguments": [
            "cc",
            "-c",
            "-DHAVE_CONFIG_H",
            "-I.",
            "-I..",
            "-g",
            "-O2",
            "-o",
            "areadlinkat.o",
            "areadlinkat.c"
        ],
        "directory": "/home/c2rust/Desktop/c_prog/tar-1.34/gnu",
        "file": "areadlinkat.c"
    },
    {
        "arguments": [
            "cc",
            "-c",
            "-DHAVE_CONFIG_H",
            "-I.",
            "-I..",
            "-g",
            "-O2",
            "-o",
            "basename-lgpl.o",
            "basename-lgpl.c"
        ],
        "directory": "/home/c2rust/Desktop/c_prog/tar-1.34/gnu",
        "file": "basename-lgpl.c"
    },
    {
        "arguments": [
            "cc",
            "-c",
            "-DHAVE_CONFIG_H",
            "-I.",
            "-I..",
            "-g",
            "-O2",
            "-o",
            "asnprintf.o",
            "asnprintf.c"
        ],
        "directory": "/home/c2rust/Desktop/c_prog/tar-1.34/gnu",
        "file": "asnprintf.c"
    },
    {
        "arguments": [
            "cc",
            "-c",
            "-DHAVE_CONFIG_H",
            "-I.",
            "-I..",
            "-g",
            "-O2",
            "-o",
            "openat-proc.o",
            "openat-proc.c"
        ],
        "directory": "/home/c2rust/Desktop/c_prog/tar-1.34/gnu",
        "file": "openat-proc.c"
    },
    {
        "arguments": [
            "cc",
            "-c",
            "-DHAVE_CONFIG_H",
            "-I.",
            "-I..",
            "-I../gnu",
            "-I../",
            "-I../gnu",
            "-I../lib",
            "-I../lib",
            "-g",
            "-O2",
            "-o",
            "exit.o",
            "exit.c"
        ],
        "directory": "/home/c2rust/Desktop/c_prog/tar-1.34/src",
        "file": "exit.c"
    },
    {
        "arguments": [
            "cc",
            "-c",
            "-DHAVE_CONFIG_H",
            "-I.",
            "-I..",
            "-g",
            "-O2",
            "-o",
            "vasnprintf.o",
            "vasnprintf.c"
        ],
        "directory": "/home/c2rust/Desktop/c_prog/tar-1.34/gnu",
        "file": "vasnprintf.c"
    },
    {
        "arguments": [
            "cc",
            "-c",
            "-DHAVE_CONFIG_H",
            "-I.",
            "-I..",
            "-g",
            "-O2",
            "-o",
            "se-label.o",
            "se-label.c"
        ],
        "directory": "/home/c2rust/Desktop/c_prog/tar-1.34/gnu",
        "file": "se-label.c"
    },
    {
        "arguments": [
            "cc",
            "-c",
            "-DHAVE_CONFIG_H",
            "-I.",
            "-I..",
            "-g",
            "-O2",
            "-o",
            "argp-eexst.o",
            "argp-eexst.c"
        ],
        "directory": "/home/c2rust/Desktop/c_prog/tar-1.34/gnu",
        "file": "argp-eexst.c"
    },
    {
        "arguments": [
            "cc",
            "-c",
            "-DHAVE_CONFIG_H",
            "-I.",
            "-I..",
            "-g",
            "-O2",
            "-o",
            "timespec.o",
            "timespec.c"
        ],
        "directory": "/home/c2rust/Desktop/c_prog/tar-1.34/gnu",
        "file": "timespec.c"
    },
    {
        "arguments": [
            "cc",
            "-c",
            "-DHAVE_CONFIG_H",
            "-I.",
            "-I..",
            "-g",
            "-O2",
            "-o",
            "xgetcwd.o",
            "xgetcwd.c"
        ],
        "directory": "/home/c2rust/Desktop/c_prog/tar-1.34/gnu",
        "file": "xgetcwd.c"
    },
    {
        "arguments": [
            "cc",
            "-c",
            "-DHAVE_CONFIG_H",
            "-I.",
            "-I..",
            "-g",
            "-O2",
            "-o",
            "bitrotate.o",
            "bitrotate.c"
        ],
        "directory": "/home/c2rust/Desktop/c_prog/tar-1.34/gnu",
        "file": "bitrotate.c"
    },
    {
        "arguments": [
            "cc",
            "-c",
            "-DHAVE_CONFIG_H",
            "-I.",
            "-I..",
            "-g",
            "-O2",
            "-o",
            "progname.o",
            "progname.c"
        ],
        "directory": "/home/c2rust/Desktop/c_prog/tar-1.34/gnu",
        "file": "progname.c"
    },
    {
        "arguments": [
            "cc",
            "-c",
            "-DHAVE_CONFIG_H",
            "-I.",
            "-I..",
            "-g",
            "-O2",
            "-o",
            "careadlinkat.o",
            "careadlinkat.c"
        ],
        "directory": "/home/c2rust/Desktop/c_prog/tar-1.34/gnu",
        "file": "careadlinkat.c"
    },
    {
        "arguments": [
            "cc",
            "-c",
            "-DHAVE_CONFIG_H",
            "-I.",
            "-I..",
            "-g",
            "-O2",
            "-o",
            "get-permissions.o",
            "get-permissions.c"
        ],
        "directory": "/home/c2rust/Desktop/c_prog/tar-1.34/gnu",
        "file": "get-permissions.c"
    },
    {
        "arguments": [
            "cc",
            "-c",
            "-DHAVE_CONFIG_H",
            "-I.",
            "-I..",
            "-g",
            "-O2",
            "-o",
            "priv-set.o",
            "priv-set.c"
        ],
        "directory": "/home/c2rust/Desktop/c_prog/tar-1.34/gnu",
        "file": "priv-set.c"
    },
    {
        "arguments": [
            "cc",
            "-c",
            "-DHAVE_CONFIG_H",
            "-I.",
            "-I..",
            "-g",
            "-O2",
            "-o",
            "chdir-long.o",
            "chdir-long.c"
        ],
        "directory": "/home/c2rust/Desktop/c_prog/tar-1.34/gnu",
        "file": "chdir-long.c"
    },
    {
        "arguments": [
            "cc",
            "-c",
            "-DHAVE_CONFIG_H",
            "-I.",
            "-I..",
            "-I../gnu",
            "-I../",
            "-I../gnu",
            "-I../lib",
            "-I../lib",
            "-g",
            "-O2",
            "-o",
            "sparse.o",
            "sparse.c"
        ],
        "directory": "/home/c2rust/Desktop/c_prog/tar-1.34/src",
        "file": "sparse.c"
    },
    {
        "arguments": [
            "cc",
            "-c",
            "-DHAVE_CONFIG_H",
            "-I.",
            "-I..",
            "-g",
            "-O2",
            "-o",
            "opendir-safer.o",
            "opendir-safer.c"
        ],
        "directory": "/home/c2rust/Desktop/c_prog/tar-1.34/gnu",
        "file": "opendir-safer.c"
    },
    {
        "arguments": [
            "cc",
            "-c",
            "-DHAVE_CONFIG_H",
            "-I.",
            "-I..",
            "-g",
            "-O2",
            "-o",
            "malloc/scratch_buffer_dupfree.o",
            "malloc/scratch_buffer_dupfree.c"
        ],
        "directory": "/home/c2rust/Desktop/c_prog/tar-1.34/gnu",
        "file": "malloc/scratch_buffer_dupfree.c"
    },
    {
        "arguments": [
            "cc",
            "-c",
            "-DHAVE_CONFIG_H",
            "-I.",
            "-I..",
            "-g",
            "-O2",
            "-o",
            "acl-internal.o",
            "acl-internal.c"
        ],
        "directory": "/home/c2rust/Desktop/c_prog/tar-1.34/gnu",
        "file": "acl-internal.c"
    },
    {
        "arguments": [
            "cc",
            "-c",
            "-DHAVE_CONFIG_H",
            "-I.",
            "-I..",
            "-I../gnu",
            "-I../",
            "-I../gnu",
            "-I../lib",
            "-I../lib",
            "-g",
            "-O2",
            "-o",
            "suffix.o",
            "suffix.c"
        ],
        "directory": "/home/c2rust/Desktop/c_prog/tar-1.34/src",
        "file": "suffix.c"
    },
    {
        "arguments": [
            "cc",
            "-c",
            "-DHAVE_CONFIG_H",
            "-I.",
            "-I..",
            "-I../gnu",
            "-I../",
            "-I../gnu",
            "-I../lib",
            "-I../lib",
            "-g",
            "-O2",
            "-o",
            "names.o",
            "names.c"
        ],
        "directory": "/home/c2rust/Desktop/c_prog/tar-1.34/src",
        "file": "names.c"
    },
    {
        "arguments": [
            "cc",
            "-c",
            "-DHAVE_CONFIG_H",
            "-I.",
            "-I..",
            "-g",
            "-O2",
            "-o",
            "xalloc-die.o",
            "xalloc-die.c"
        ],
        "directory": "/home/c2rust/Desktop/c_prog/tar-1.34/gnu",
        "file": "xalloc-die.c"
    },
    {
        "arguments": [
            "cc",
            "-c",
            "-DHAVE_CONFIG_H",
            "-I.",
            "-I..",
            "-g",
            "-O2",
            "-o",
            "time_rz.o",
            "time_rz.c"
        ],
        "directory": "/home/c2rust/Desktop/c_prog/tar-1.34/gnu",
        "file": "time_rz.c"
    },
    {
        "arguments": [
            "cc",
            "-c",
            "-DHAVE_CONFIG_H",
            "-I.",
            "-I..",
            "-g",
            "-O2",
            "-o",
            "argp-xinl.o",
            "argp-xinl.c"
        ],
        "directory": "/home/c2rust/Desktop/c_prog/tar-1.34/gnu",
        "file": "argp-xinl.c"
    },
    {
        "arguments": [
            "cc",
            "-c",
            "-DHAVE_CONFIG_H",
            "-I.",
            "-I..",
            "-g",
            "-O2",
            "-o",
            "offtostr.o",
            "offtostr.c"
        ],
        "directory": "/home/c2rust/Desktop/c_prog/tar-1.34/gnu",
        "file": "offtostr.c"
    },
    {
        "arguments": [
            "cc",
            "-c",
            "-DHAVE_CONFIG_H",
            "-I.",
            "-I..",
            "-g",
            "-O2",
            "-o",
            "malloc/scratch_buffer_set_array_size.o",
            "malloc/scratch_buffer_set_array_size.c"
        ],
        "directory": "/home/c2rust/Desktop/c_prog/tar-1.34/gnu",
        "file": "malloc/scratch_buffer_set_array_size.c"
    },
    {
        "arguments": [
            "cc",
            "-c",
            "-DHAVE_CONFIG_H",
            "-I.",
            "-I..",
            "-g",
            "-O2",
            "-o",
            "timespec-sub.o",
            "timespec-sub.c"
        ],
        "directory": "/home/c2rust/Desktop/c_prog/tar-1.34/gnu",
        "file": "timespec-sub.c"
    },
    {
        "arguments": [
            "cc",
            "-c",
            "-DHAVE_CONFIG_H",
            "-I.",
            "-I..",
            "-g",
            "-O2",
            "-o",
            "dup-safer-flag.o",
            "dup-safer-flag.c"
        ],
        "directory": "/home/c2rust/Desktop/c_prog/tar-1.34/gnu",
        "file": "dup-safer-flag.c"
    },
    {
        "arguments": [
            "cc",
            "-c",
            "-DHAVE_CONFIG_H",
            "-I.",
            "-I..",
            "-g",
            "-O2",
            "-o",
            "savedir.o",
            "savedir.c"
        ],
        "directory": "/home/c2rust/Desktop/c_prog/tar-1.34/gnu",
        "file": "savedir.c"
    },
    {
        "arguments": [
            "cc",
            "-c",
            "-DHAVE_CONFIG_H",
            "-I.",
            "-I..",
            "-g",
            "-O2",
            "-o",
            "argp-fs-xinl.o",
            "argp-fs-xinl.c"
        ],
        "directory": "/home/c2rust/Desktop/c_prog/tar-1.34/gnu",
        "file": "argp-fs-xinl.c"
    },
    {
        "arguments": [
            "cc",
            "-c",
            "-DHAVE_CONFIG_H",
            "-I.",
            "-I..",
            "-g",
            "-O2",
            "-o",
            "mbchar.o",
            "mbchar.c"
        ],
        "directory": "/home/c2rust/Desktop/c_prog/tar-1.34/gnu",
        "file": "mbchar.c"
    },
    {
        "arguments": [
            "cc",
            "-c",
            "-DHAVE_CONFIG_H",
            "-I.",
            "-I..",
            "-I../gnu",
            "-I../",
            "-I../gnu",
            "-I../lib",
            "-I../lib",
            "-g",
            "-O2",
            "-o",
            "xattrs.o",
            "xattrs.c"
        ],
        "directory": "/home/c2rust/Desktop/c_prog/tar-1.34/src",
        "file": "xattrs.c"
    },
    {
        "arguments": [
            "cc",
            "-c",
            "-DHAVE_CONFIG_H",
            "-I.",
            "-I..",
            "-I../gnu",
            "-I../",
            "-I../gnu",
            "-I../lib",
            "-I../lib",
            "-g",
            "-O2",
            "-o",
            "xheader.o",
            "xheader.c"
        ],
        "directory": "/home/c2rust/Desktop/c_prog/tar-1.34/src",
        "file": "xheader.c"
    },
    {
        "arguments": [
            "cc",
            "-c",
            "-DHAVE_CONFIG_H",
            "-I.",
            "-I..",
            "-g",
            "-O2",
            "-o",
            "inttostr.o",
            "inttostr.c"
        ],
        "directory": "/home/c2rust/Desktop/c_prog/tar-1.34/gnu",
        "file": "inttostr.c"
    },
    {
        "arguments": [
            "cc",
            "-c",
            "-DHAVE_CONFIG_H",
            "-I.",
            "-I..",
            "-g",
            "-O2",
            "-o",
            "version-etc-fsf.o",
            "version-etc-fsf.c"
        ],
        "directory": "/home/c2rust/Desktop/c_prog/tar-1.34/gnu",
        "file": "version-etc-fsf.c"
    },
    {
        "arguments": [
            "cc",
            "-c",
            "-DHAVE_CONFIG_H",
            "-I.",
            "-I..",
            "-g",
            "-O2",
            "-o",
            "xstrndup.o",
            "xstrndup.c"
        ],
        "directory": "/home/c2rust/Desktop/c_prog/tar-1.34/gnu",
        "file": "xstrndup.c"
    },
    {
        "arguments": [
            "cc",
            "-c",
            "-DHAVE_CONFIG_H",
            "-I.",
            "-I..",
            "-g",
            "-O2",
            "-o",
            "unlinkdir.o",
            "unlinkdir.c"
        ],
        "directory": "/home/c2rust/Desktop/c_prog/tar-1.34/gnu",
        "file": "unlinkdir.c"
    },
    {
        "arguments": [
            "cc",
            "-c",
            "-DHAVE_CONFIG_H",
            "-I.",
            "-I..",
            "-g",
            "-O2",
            "-o",
            "argp-pv.o",
            "argp-pv.c"
        ],
        "directory": "/home/c2rust/Desktop/c_prog/tar-1.34/gnu",
        "file": "argp-pv.c"
    },
    {
        "arguments": [
            "cc",
            "-c",
            "-DHAVE_CONFIG_H",
            "-I.",
            "-I..",
            "-g",
            "-O2",
            "-o",
            "safe-read.o",
            "safe-read.c"
        ],
        "directory": "/home/c2rust/Desktop/c_prog/tar-1.34/gnu",
        "file": "safe-read.c"
    },
    {
        "arguments": [
            "cc",
            "-c",
            "-DHAVE_CONFIG_H",
            "-I.",
            "-I..",
            "-I../gnu",
            "-I../",
            "-I../gnu",
            "-I../lib",
            "-I../lib",
            "-g",
            "-O2",
            "-o",
            "misc.o",
            "misc.c"
        ],
        "directory": "/home/c2rust/Desktop/c_prog/tar-1.34/src",
        "file": "misc.c"
    },
    {
        "arguments": [
            "cc",
            "-c",
            "-DHAVE_CONFIG_H",
            "-I.",
            "-I..",
            "-g",
            "-O2",
            "-o",
            "fcntl.o",
            "fcntl.c"
        ],
        "directory": "/home/c2rust/Desktop/c_prog/tar-1.34/gnu",
        "file": "fcntl.c"
    },
    {
        "arguments": [
            "cc",
            "-c",
            "-DHAVE_CONFIG_H",
            "-I.",
            "-I..",
            "-g",
            "-O2",
            "-o",
            "human.o",
            "human.c"
        ],
        "directory": "/home/c2rust/Desktop/c_prog/tar-1.34/gnu",
        "file": "human.c"
    },
    {
        "arguments": [
            "cc",
            "-c",
            "-DHAVE_CONFIG_H",
            "-I.",
            "-I..",
            "-g",
            "-O2",
            "-o",
            "argp-pvh.o",
            "argp-pvh.c"
        ],
        "directory": "/home/c2rust/Desktop/c_prog/tar-1.34/gnu",
        "file": "argp-pvh.c"
    },
    {
        "arguments": [
            "cc",
            "-c",
            "-DHAVE_CONFIG_H",
            "-I.",
            "-I..",
            "-g",
            "-O2",
            "-o",
            "argp-version-etc.o",
            "argp-version-etc.c"
        ],
        "directory": "/home/c2rust/Desktop/c_prog/tar-1.34/gnu",
        "file": "argp-version-etc.c"
    },
    {
        "arguments": [
            "cc",
            "-c",
            "-DHAVE_CONFIG_H",
            "-I.",
            "-I..",
            "-g",
            "-O2",
            "-o",
            "basename.o",
            "basename.c"
        ],
        "directory": "/home/c2rust/Desktop/c_prog/tar-1.34/gnu",
        "file": "basename.c"
    },
    {
        "arguments": [
            "cc",
            "-c",
            "-DHAVE_CONFIG_H",
            "-I.",
            "-I..",
            "-g",
            "-O2",
            "-o",
            "stripslash.o",
            "stripslash.c"
        ],
        "directory": "/home/c2rust/Desktop/c_prog/tar-1.34/gnu",
        "file": "stripslash.c"
    },
    {
        "arguments": [
            "cc",
            "-c",
            "-DHAVE_CONFIG_H",
            "-I.",
            "-I..",
            "-g",
            "-O2",
            "-o",
            "pipe-safer.o",
            "pipe-safer.c"
        ],
        "directory": "/home/c2rust/Desktop/c_prog/tar-1.34/gnu",
        "file": "pipe-safer.c"
    },
    {
        "arguments": [
            "cc",
            "-c",
            "-DHAVE_CONFIG_H",
            "-I.",
            "-I..",
            "-g",
            "-O2",
            "-o",
            "regex.o",
            "regex.c"
        ],
        "directory": "/home/c2rust/Desktop/c_prog/tar-1.34/gnu",
        "file": "regex.c"
    },
    {
        "arguments": [
            "cc",
            "-c",
            "-DHAVE_CONFIG_H",
            "-I.",
            "-I..",
            "-I../gnu",
            "-I../",
            "-I../gnu",
            "-I../lib",
            "-I../lib",
            "-g",
            "-O2",
            "-o",
            "utf8.o",
            "utf8.c"
        ],
        "directory": "/home/c2rust/Desktop/c_prog/tar-1.34/src",
        "file": "utf8.c"
    },
    {
        "arguments": [
            "cc",
            "-c",
            "-DHAVE_CONFIG_H",
            "-I.",
            "-I..",
            "-g",
            "-O2",
            "-o",
            "c-ctype.o",
            "c-ctype.c"
        ],
        "directory": "/home/c2rust/Desktop/c_prog/tar-1.34/gnu",
        "file": "c-ctype.c"
    },
    {
        "arguments": [
            "cc",
            "-c",
            "-DHAVE_CONFIG_H",
            "-I.",
            "-I..",
            "-g",
            "-O2",
            "-o",
            "hash.o",
            "hash.c"
        ],
        "directory": "/home/c2rust/Desktop/c_prog/tar-1.34/gnu",
        "file": "hash.c"
    },
    {
        "arguments": [
            "cc",
            "-c",
            "-DHAVE_CONFIG_H",
            "-I.",
            "-I..",
            "-g",
            "-O2",
            "-o",
            "fd-hook.o",
            "fd-hook.c"
        ],
        "directory": "/home/c2rust/Desktop/c_prog/tar-1.34/gnu",
        "file": "fd-hook.c"
    },
    {
        "arguments": [
            "cc",
            "-c",
            "-DHAVE_CONFIG_H",
            "-I.",
            "-I..",
            "-I../gnu",
            "-I../",
            "-I../gnu",
            "-I../lib",
            "-I../lib",
            "-g",
            "-O2",
            "-o",
            "delete.o",
            "delete.c"
        ],
        "directory": "/home/c2rust/Desktop/c_prog/tar-1.34/src",
        "file": "delete.c"
    },
    {
        "arguments": [
            "cc",
            "-c",
            "-DHAVE_CONFIG_H",
            "-I.",
            "-I..",
            "-I../gnu",
            "-I../",
            "-I../gnu",
            "-g",
            "-O2",
            "-o",
            "wordsplit.o",
            "wordsplit.c"
        ],
        "directory": "/home/c2rust/Desktop/c_prog/tar-1.34/lib",
        "file": "wordsplit.c"
    },
    {
        "arguments": [
            "cc",
            "-c",
            "-DHAVE_CONFIG_H",
            "-I.",
            "-I..",
            "-g",
            "-O2",
            "-o",
            "fchmodat.o",
            "fchmodat.c"
        ],
        "directory": "/home/c2rust/Desktop/c_prog/tar-1.34/gnu",
        "file": "fchmodat.c"
    },
    {
        "arguments": [
            "cc",
            "-c",
            "-DHAVE_CONFIG_H",
            "-I.",
            "-I..",
            "-g",
            "-O2",
            "-o",
            "version-etc.o",
            "version-etc.c"
        ],
        "directory": "/home/c2rust/Desktop/c_prog/tar-1.34/gnu",
        "file": "version-etc.c"
    },
    {
        "arguments": [
            "cc",
            "-c",
            "-DHAVE_CONFIG_H",
            "-I.",
            "-I..",
            "-I../gnu",
            "-I../",
            "-I../gnu",
            "-I../lib",
            "-I../lib",
            "-g",
            "-O2",
            "-o",
            "create.o",
            "create.c"
        ],
        "directory": "/home/c2rust/Desktop/c_prog/tar-1.34/src",
        "file": "create.c"
    },
    {
        "arguments": [
            "cc",
            "-c",
            "-DHAVE_CONFIG_H",
            "-I.",
            "-I..",
            "-g",
            "-O2",
            "-o",
            "fd-safer-flag.o",
            "fd-safer-flag.c"
        ],
        "directory": "/home/c2rust/Desktop/c_prog/tar-1.34/gnu",
        "file": "fd-safer-flag.c"
    },
    {
        "arguments": [
            "cc",
            "-c",
            "-DHAVE_CONFIG_H",
            "-I.",
            "-I..",
            "-g",
            "-O2",
            "-o",
            "stat-time.o",
            "stat-time.c"
        ],
        "directory": "/home/c2rust/Desktop/c_prog/tar-1.34/gnu",
        "file": "stat-time.c"
    },
    {
        "arguments": [
            "cc",
            "-c",
            "-DHAVE_CONFIG_H",
            "-I.",
            "-I..",
            "-g",
            "-O2",
            "-o",
            "imaxtostr.o",
            "imaxtostr.c"
        ],
        "directory": "/home/c2rust/Desktop/c_prog/tar-1.34/gnu",
        "file": "imaxtostr.c"
    },
    {
        "arguments": [
            "cc",
            "-c",
            "-DHAVE_CONFIG_H",
            "-I.",
            "-I..",
            "-I../gnu",
            "-I../",
            "-I../gnu",
            "-g",
            "-O2",
            "-o",
            "paxerror.o",
            "paxerror.c"
        ],
        "directory": "/home/c2rust/Desktop/c_prog/tar-1.34/lib",
        "file": "paxerror.c"
    },
    {
        "arguments": [
            "cc",
            "-c",
            "-DHAVE_CONFIG_H",
            "-I.",
            "-I..",
            "-I../gnu",
            "-I../",
            "-I../gnu",
            "-I../lib",
            "-I../lib",
            "-g",
            "-O2",
            "-o",
            "system.o",
            "system.c"
        ],
        "directory": "/home/c2rust/Desktop/c_prog/tar-1.34/src",
        "file": "system.c"
    },
    {
        "arguments": [
            "cc",
            "-c",
            "-DHAVE_CONFIG_H",
            "-I.",
            "-I..",
            "-g",
            "-O2",
            "-o",
            "dirname.o",
            "dirname.c"
        ],
        "directory": "/home/c2rust/Desktop/c_prog/tar-1.34/gnu",
        "file": "dirname.c"
    },
    {
        "arguments": [
            "cc",
            "-c",
            "-DHAVE_CONFIG_H",
            "-I.",
            "-I..",
            "-g",
            "-O2",
            "-o",
            "mbuiter.o",
            "mbuiter.c"
        ],
        "directory": "/home/c2rust/Desktop/c_prog/tar-1.34/gnu",
        "file": "mbuiter.c"
    },
    {
        "arguments": [
            "cc",
            "-c",
            "-DHAVE_CONFIG_H",
            "-I.",
            "-I..",
            "-I../gnu",
            "-I../",
            "-I../gnu",
            "-I../lib",
            "-I../lib",
            "-g",
            "-O2",
            "-o",
            "list.o",
            "list.c"
        ],
        "directory": "/home/c2rust/Desktop/c_prog/tar-1.34/src",
        "file": "list.c"
    },
    {
        "arguments": [
            "cc",
            "-c",
            "-DHAVE_CONFIG_H",
            "-I.",
            "-I..",
            "-I../gnu",
            "-I../",
            "-I../gnu",
            "-I../lib",
            "-I../lib",
            "-g",
            "-O2",
            "-o",
            "warning.o",
            "warning.c"
        ],
        "directory": "/home/c2rust/Desktop/c_prog/tar-1.34/src",
        "file": "warning.c"
    },
    {
        "arguments": [
            "cc",
            "-c",
            "-DHAVE_CONFIG_H",
            "-I.",
            "-I..",
            "-I../gnu",
            "-I../",
            "-I../gnu",
            "-I../lib",
            "-I../lib",
            "-g",
            "-O2",
            "-o",
            "compare.o",
            "compare.c"
        ],
        "directory": "/home/c2rust/Desktop/c_prog/tar-1.34/src",
        "file": "compare.c"
    },
    {
        "arguments": [
            "cc",
            "-c",
            "-DHAVE_CONFIG_H",
            "-I.",
            "-I..",
            "-g",
            "-O2",
            "-o",
            "openat-die.o",
            "openat-die.c"
        ],
        "directory": "/home/c2rust/Desktop/c_prog/tar-1.34/gnu",
        "file": "openat-die.c"
    },
    {
        "arguments": [
            "cc",
            "-c",
            "-DHAVE_CONFIG_H",
            "-I.",
            "-I..",
            "-g",
            "-O2",
            "-o",
            "safe-write.o",
            "safe-write.c"
        ],
        "directory": "/home/c2rust/Desktop/c_prog/tar-1.34/gnu",
        "file": "safe-write.c"
    },
    {
        "arguments": [
            "cc",
            "-c",
            "-DHAVE_CONFIG_H",
            "-I.",
            "-I..",
            "-g",
            "-O2",
            "-o",
            "xsize.o",
            "xsize.c"
        ],
        "directory": "/home/c2rust/Desktop/c_prog/tar-1.34/gnu",
        "file": "xsize.c"
    },
    {
        "arguments": [
            "cc",
            "-c",
            "-DHAVE_CONFIG_H",
            "-I.",
            "-I..",
            "-g",
            "-O2",
            "-o",
            "gettime.o",
            "gettime.c"
        ],
        "directory": "/home/c2rust/Desktop/c_prog/tar-1.34/gnu",
        "file": "gettime.c"
    },
    {
        "arguments": [
            "cc",
            "-c",
            "-DHAVE_CONFIG_H",
            "-I.",
            "-I..",
            "-g",
            "-O2",
            "-o",
            "fdutimensat.o",
            "fdutimensat.c"
        ],
        "directory": "/home/c2rust/Desktop/c_prog/tar-1.34/gnu",
        "file": "fdutimensat.c"
    },
    {
        "arguments": [
            "cc",
            "-c",
            "-DHAVE_CONFIG_H",
            "-I.",
            "-I..",
            "-I../gnu",
            "-I../",
            "-I../gnu",
            "-I../lib",
            "-I../lib",
            "-g",
            "-O2",
            "-o",
            "buffer.o",
            "buffer.c"
        ],
        "directory": "/home/c2rust/Desktop/c_prog/tar-1.34/src",
        "file": "buffer.c"
    },
    {
        "arguments": [
            "cc",
            "-c",
            "-DHAVE_CONFIG_H",
            "-I.",
            "-I..",
            "-g",
            "-O2",
            "-o",
            "backupfile.o",
            "backupfile.c"
        ],
        "directory": "/home/c2rust/Desktop/c_prog/tar-1.34/gnu",
        "file": "backupfile.c"
    },
    {
        "arguments": [
            "cc",
            "-c",
            "-DHAVE_CONFIG_H",
            "-I.",
            "-I..",
            "-g",
            "-O2",
            "-o",
            "se-context.o",
            "se-context.c"
        ],
        "directory": "/home/c2rust/Desktop/c_prog/tar-1.34/gnu",
        "file": "se-context.c"
    },
    {
        "arguments": [
            "cc",
            "-c",
            "-DHAVE_CONFIG_H",
            "-I.",
            "-I..",
            "-g",
            "-O2",
            "-o",
            "parse-datetime.o",
            "parse-datetime.c"
        ],
        "directory": "/home/c2rust/Desktop/c_prog/tar-1.34/gnu",
        "file": "parse-datetime.c"
    },
    {
        "arguments": [
            "cc",
            "-c",
            "-DHAVE_CONFIG_H",
            "-I.",
            "-I..",
            "-g",
            "-O2",
            "-o",
            "xstrtol.o",
            "xstrtol.c"
        ],
        "directory": "/home/c2rust/Desktop/c_prog/tar-1.34/gnu",
        "file": "xstrtol.c"
    },
    {
        "arguments": [
            "cc",
            "-c",
            "-DHAVE_CONFIG_H",
            "-I.",
            "-I..",
            "-I../gnu",
            "-I../",
            "-I../gnu",
            "-I../lib",
            "-I../lib",
            "-g",
            "-O2",
            "-o",
            "exclist.o",
            "exclist.c"
        ],
        "directory": "/home/c2rust/Desktop/c_prog/tar-1.34/src",
        "file": "exclist.c"
    },
    {
        "arguments": [
            "cc",
            "-c",
            "-DHAVE_CONFIG_H",
            "-I.",
            "-I..",
            "-g",
            "-O2",
            "-o",
            "set-permissions.o",
            "set-permissions.c"
        ],
        "directory": "/home/c2rust/Desktop/c_prog/tar-1.34/gnu",
        "file": "set-permissions.c"
    },
    {
        "arguments": [
            "cc",
            "-c",
            "-DHAVE_CONFIG_H",
            "-I.",
            "-I..",
            "-g",
            "-O2",
            "-o",
            "close-stream.o",
            "close-stream.c"
        ],
        "directory": "/home/c2rust/Desktop/c_prog/tar-1.34/gnu",
        "file": "close-stream.c"
    },
    {
        "arguments": [
            "cc",
            "-c",
            "-DHAVE_CONFIG_H",
            "-I.",
            "-I..",
            "-g",
            "-O2",
            "-o",
            "exitfail.o",
            "exitfail.c"
        ],
        "directory": "/home/c2rust/Desktop/c_prog/tar-1.34/gnu",
        "file": "exitfail.c"
    },
    {
        "arguments": [
            "cc",
            "-c",
            "-DHAVE_CONFIG_H",
            "-I.",
            "-I..",
            "-g",
            "-O2",
            "-o",
            "areadlinkat-with-size.o",
            "areadlinkat-with-size.c"
        ],
        "directory": "/home/c2rust/Desktop/c_prog/tar-1.34/gnu",
        "file": "areadlinkat-with-size.c"
    },
    {
        "arguments": [
            "cc",
            "-c",
            "-DHAVE_CONFIG_H",
            "-I.",
            "-I..",
            "-g",
            "-O2",
            "-o",
            "exclude.o",
            "exclude.c"
        ],
        "directory": "/home/c2rust/Desktop/c_prog/tar-1.34/gnu",
        "file": "exclude.c"
    },
    {
        "arguments": [
            "cc",
            "-c",
            "-DHAVE_CONFIG_H",
            "-I.",
            "-I..",
            "-I../gnu",
            "-I../",
            "-I../gnu",
            "-I../lib",
            "-I../lib",
            "-g",
            "-O2",
            "-o",
            "unlink.o",
            "unlink.c"
        ],
        "directory": "/home/c2rust/Desktop/c_prog/tar-1.34/src",
        "file": "unlink.c"
    },
    {
        "arguments": [
            "cc",
            "-c",
            "-DHAVE_CONFIG_H",
            "-I.",
            "-I..",
            "-g",
            "-O2",
            "-o",
            "xmalloc.o",
            "xmalloc.c"
        ],
        "directory": "/home/c2rust/Desktop/c_prog/tar-1.34/gnu",
        "file": "xmalloc.c"
    },
    {
        "arguments": [
            "cc",
            "-c",
            "-DHAVE_CONFIG_H",
            "-I.",
            "-I..",
            "-g",
            "-O2",
            "-o",
            "modechange.o",
            "modechange.c"
        ],
        "directory": "/home/c2rust/Desktop/c_prog/tar-1.34/gnu",
        "file": "modechange.c"
    },
    {
        "arguments": [
            "cc",
            "-c",
            "-DHAVE_CONFIG_H",
            "-I.",
            "-I..",
            "-g",
            "-O2",
            "-o",
            "mktime.o",
            "mktime.c"
        ],
        "directory": "/home/c2rust/Desktop/c_prog/tar-1.34/gnu",
        "file": "mktime.c"
    },
    {
        "arguments": [
            "cc",
            "-c",
            "-DHAVE_CONFIG_H",
            "-I.",
            "-I..",
            "-g",
            "-O2",
            "-o",
            "filenamecat-lgpl.o",
            "filenamecat-lgpl.c"
        ],
        "directory": "/home/c2rust/Desktop/c_prog/tar-1.34/gnu",
        "file": "filenamecat-lgpl.c"
    },
    {
        "arguments": [
            "cc",
            "-c",
            "-DHAVE_CONFIG_H",
            "-I.",
            "-I..",
            "-g",
            "-O2",
            "-o",
            "wctype-h.o",
            "wctype-h.c"
        ],
        "directory": "/home/c2rust/Desktop/c_prog/tar-1.34/gnu",
        "file": "wctype-h.c"
    },
    {
        "arguments": [
            "cc",
            "-c",
            "-DHAVE_CONFIG_H",
            "-I.",
            "-I..",
            "-g",
            "-O2",
            "-o",
            "free.o",
            "free.c"
        ],
        "directory": "/home/c2rust/Desktop/c_prog/tar-1.34/gnu",
        "file": "free.c"
    },
    {
        "arguments": [
            "cc",
            "-c",
            "-DHAVE_CONFIG_H",
            "-I.",
            "-I..",
            "-g",
            "-O2",
            "-o",
            "c-strcasecmp.o",
            "c-strcasecmp.c"
        ],
        "directory": "/home/c2rust/Desktop/c_prog/tar-1.34/gnu",
        "file": "c-strcasecmp.c"
    },
    {
        "arguments": [
            "cc",
            "-c",
            "-DHAVE_CONFIG_H",
            "-I.",
            "-I..",
            "-g",
            "-O2",
            "-o",
            "getprogname.o",
            "getprogname.c"
        ],
        "directory": "/home/c2rust/Desktop/c_prog/tar-1.34/gnu",
        "file": "getprogname.c"
    }
]